gocept.logging-1.0-py3.11-nspkg.pth
gocept/logging/__init__.py
gocept/logging/adapter.py
gocept/logging/argumentparser.py
gocept/logging/formatter.py
gocept/logging/testing.py
gocept/logging/tests/__init__.py
gocept/logging/tests/test_adapter.py
gocept/logging/tests/test_argumentparser.py
gocept/logging/tests/test_formatter.py
gocept/logging/tests/test_testing.py
gocept.logging-1.0.dist-info/LICENSE.txt
gocept.logging-1.0.dist-info/METADATA
gocept.logging-1.0.dist-info/WHEEL
gocept.logging-1.0.dist-info/namespace_packages.txt
gocept.logging-1.0.dist-info/top_level.txt
gocept.logging-1.0.dist-info/RECORD
