Metadata-Version: 2.1
Name: gocept.logging
Version: 1.0
Summary: Infrastructure for semi-structured log messages.
Home-page: https://github.com/gocept/gocept.logging
Author: gocept <mail@gocept.com>
Author-email: mail@gocept.com
License: ZPL 2.1
Classifier: License :: OSI Approved :: Zope Public License
Classifier: Programming Language :: Python
Classifier: Programming Language :: Python :: 3
Classifier: Programming Language :: Python :: 3.7
Classifier: Programming Language :: Python :: 3.8
Classifier: Programming Language :: Python :: 3.9
Classifier: Programming Language :: Python :: 3.10
Classifier: Programming Language :: Python :: 3.11
Classifier: Programming Language :: Python :: Implementation :: CPython
Classifier: Programming Language :: Python :: Implementation :: PyPy
Requires-Python: >=3.7
License-File: LICENSE.txt
Requires-Dist: setuptools
Provides-Extra: test
Requires-Dist: mock ; extra == 'test'
